spacy-3.8.10.dist-info/RECORD
spacy-3.8.10.dist-info/WHEEL
spacy-3.8.10.dist-info/entry_points.txt
spacy-3.8.10.dist-info/top_level.txt
spacy-3.8.10.dist-info/METADATA
spacy-3.8.10.dist-info/licenses/LICENSE
spacy/typedefs.pxd
spacy/default_config_pretraining.cfg
spacy/vocab.pxd
spacy/git_info.py
spacy/compat.py
spacy/strings.pyi
spacy/lexeme.pyx
spacy/morphology.pxd
spacy/parts_of_speech.cpython-313-darwin.so
spacy/util.py
spacy/__init__.pxd
spacy/strings.pxd
spacy/vocab.pyi
spacy/tokenizer.pxd
spacy/attrs.pxd
spacy/__init__.py
spacy/parts_of_speech.pyx
spacy/lookups.py
spacy/about.py
spacy/symbols.pyx
spacy/symbols.cpython-313-darwin.so
spacy/morphology.cpython-313-darwin.so
spacy/symbols.pxd
spacy/parts_of_speech.pxd
spacy/schemas.py
spacy/tokenizer.pyx
spacy/tokenizer.cpython-313-darwin.so
spacy/attrs.pyx
spacy/strings.pyx
spacy/language.py
spacy/vocab.cpython-313-darwin.so
spacy/pipe_analysis.py
spacy/lexeme.pyi
spacy/py.typed
spacy/lexeme.cpython-313-darwin.so
spacy/registrations.py
spacy/morphology.pyx
spacy/structs.pxd
spacy/errors.py
spacy/lexeme.pxd
spacy/vectors.cpython-313-darwin.so
spacy/ty.py
spacy/vocab.pyx
spacy/vectors.pyx
spacy/attrs.cpython-313-darwin.so
spacy/typedefs.pyx
spacy/strings.cpython-313-darwin.so
spacy/__main__.py
spacy/default_config.cfg
spacy/scorer.py
spacy/glossary.py
spacy/displacy/render.py
spacy/displacy/__init__.py
spacy/displacy/templates.py
spacy/pipeline/functions.py
spacy/pipeline/pipe.pxd
spacy/pipeline/tok2vec.py
spacy/pipeline/lemmatizer.py
spacy/pipeline/pipe.cpython-313-darwin.so
spacy/pipeline/edit_tree_lemmatizer.py
spacy/pipeline/ner.cpython-313-darwin.so
spacy/pipeline/trainable_pipe.cpython-313-darwin.so
spacy/pipeline/entityruler.py
spacy/pipeline/transition_parser.pxd
spacy/pipeline/senter.pyx
spacy/pipeline/spancat.py
spacy/pipeline/attributeruler.py
spacy/pipeline/__init__.py
spacy/pipeline/trainable_pipe.pxd
spacy/pipeline/span_ruler.py
spacy/pipeline/factories.py
spacy/pipeline/pipe.pyi
spacy/pipeline/morphologizer.cpython-313-darwin.so
spacy/pipeline/morphologizer.pyx
spacy/pipeline/trainable_pipe.pyx
spacy/pipeline/multitask.pyx
