Metadata-Version: 2.4
Name: spacy
Version: 3.8.10
Summary: Industrial-strength Natural Language Processing (NLP) in Python
Home-page: https://spacy.io
Author: Explosion
Author-email: contact@explosion.ai
License: MIT
Project-URL: Release notes, https://github.com/explosion/spaCy/releases
Project-URL: Source, https://github.com/explosion/spaCy
Classifier: Development Status :: 5 - Production/Stable
Classifier: Environment :: Console
Classifier: Intended Audience :: Developers
Classifier: Intended Audience :: Science/Research
Classifier: License :: OSI Approved :: MIT License
Classifier: Operating System :: POSIX :: Linux
Classifier: Operating System :: MacOS :: MacOS X
Classifier: Operating System :: Microsoft :: Windows
Classifier: Programming Language :: Cython
Classifier: Programming Language :: Python :: 3
Classifier: Programming Language :: Python :: 3.9
Classifier: Programming Language :: Python :: 3.10
Classifier: Programming Language :: Python :: 3.11
Classifier: Programming Language :: Python :: 3.12
Classifier: Programming Language :: Python :: 3.13
Classifier: Topic :: Scientific/Engineering
Requires-Python: <3.15,>=3.9
License-File: LICENSE
Requires-Dist: spacy-legacy<3.1.0,>=3.0.11
Requires-Dist: spacy-loggers<2.0.0,>=1.0.0
Requires-Dist: murmurhash<1.1.0,>=0.28.0
Requires-Dist: cymem<2.1.0,>=2.0.2
Requires-Dist: preshed<3.1.0,>=3.0.2
Requires-Dist: thinc<8.4.0,>=8.3.4
Requires-Dist: wasabi<1.2.0,>=0.9.1
Requires-Dist: srsly<3.0.0,>=2.4.3
Requires-Dist: catalogue<2.1.0,>=2.0.6
Requires-Dist: weasel<0.5.0,>=0.4.2
Requires-Dist: typer-slim<1.0.0,>=0.3.0
Requires-Dist: tqdm<5.0.0,>=4.38.0
Requires-Dist: numpy>=1.15.0; python_version < "3.9"
Requires-Dist: numpy>=1.19.0; python_version >= "3.9"
Requires-Dist: requests<3.0.0,>=2.13.0
Requires-Dist: pydantic!=1.8,!=1.8.1,<3.0.0,>=1.7.4
Requires-Dist: jinja2
Requires-Dist: setuptools
Requires-Dist: packaging>=20.0
Provides-Extra: lookups
Requires-Dist: spacy_lookups_data<1.1.0,>=1.0.3; extra == "lookups"
Provides-Extra: transformers
Requires-Dist: spacy_transformers<1.4.0,>=1.1.2; extra == "transformers"
Provides-Extra: cuda
Requires-Dist: cupy<13.0.0,>=5.0.0b4; extra == "cuda"
Provides-Extra: cuda80
Requires-Dist: cupy-cuda80<13.0.0,>=5.0.0b4; extra == "cuda80"
Provides-Extra: cuda90
Requires-Dist: cupy-cuda90<13.0.0,>=5.0.0b4; extra == "cuda90"
Provides-Extra: cuda91
Requires-Dist: cupy-cuda91<13.0.0,>=5.0.0b4; extra == "cuda91"
Provides-Extra: cuda92
Requires-Dist: cupy-cuda92<13.0.0,>=5.0.0b4; extra == "cuda92"
Provides-Extra: cuda100
Requires-Dist: cupy-cuda100<13.0.0,>=5.0.0b4; extra == "cuda100"
Provides-Extra: cuda101
Requires-Dist: cupy-cuda101<13.0.0,>=5.0.0b4; extra == "cuda101"
Provides-Extra: cuda102
Requires-Dist: cupy-cuda102<13.0.0,>=5.0.0b4; extra == "cuda102"
Provides-Extra: cuda110
Requires-Dist: cupy-cuda110<13.0.0,>=5.0.0b4; extra == "cuda110"
Provides-Extra: cuda111
Requires-Dist: cupy-cuda111<13.0.0,>=5.0.0b4; extra == "cuda111"
Provides-Extra: cuda112
Requires-Dist: cupy-cuda112<13.0.0,>=5.0.0b4; extra == "cuda112"
Provides-Extra: cuda113
Requires-Dist: cupy-cuda113<13.0.0,>=5.0.0b4; extra == "cuda113"
Provides-Extra: cuda114
Requires-Dist: cupy-cuda114<13.0.0,>=5.0.0b4; extra == "cuda114"
Provides-Extra: cuda115
Requires-Dist: cupy-cuda115<13.0.0,>=5.0.0b4; extra == "cuda115"
Provides-Extra: cuda116
Requires-Dist: cupy-cuda116<13.0.0,>=5.0.0b4; extra == "cuda116"
Provides-Extra: cuda117
Requires-Dist: cupy-cuda117<13.0.0,>=5.0.0b4; extra == "cuda117"
Provides-Extra: cuda11x
Requires-Dist: cupy-cuda11x<13.0.0,>=11.0.0; extra == "cuda11x"
Provides-Extra: cuda12x
Requires-Dist: cupy-cuda12x<13.0.0,>=11.5.0; extra == "cuda12x"
Provides-Extra: cuda-autodetect
Requires-Dist: cupy-wheel<13.0.0,>=11.0.0; extra == "cuda-autodetect"
Provides-Extra: apple
Requires-Dist: thinc-apple-ops<2.0.0,>=1.0.0; extra == "apple"
Provides-Extra: ja
Requires-Dist: sudachipy!=0.6.1,>=0.5.2; extra == "ja"
Requires-Dist: sudachidict_core>=20211220; extra == "ja"
Provides-Extra: ko
Requires-Dist: natto-py>=0.9.0; extra == "ko"
Provides-Extra: th
Requires-Dist: pythainlp>=2.0; extra == "th"
Dynamic: license-file
